Workbook

Sheet FINAL PAY OUT
A2: Row Labels | B2: Center Alignment | C2: NPD | D2: OSA | E2: POSM | F2: SOS vs SOM | G2: Average Score | H2: Score
A3: 2k shoppers | B3: 1 | C3: 0.77777778 | D3: 1 | E3: 1 | F3: =VLOOKUP(A:A,'SOS VS SOM'!A:E,4,FALSE) -> 0 | G3: =AVERAGE(B3:F3) -> 0.75555556 | H3: =IF(G3>=60%,"pay","don't pay") -> pay
A4: Abra Shopping Centre | B4: 1 | C4: 1 | D4: 1 | E4: 1 | F4: =VLOOKUP(A:A,'SOS VS SOM'!A:E,4,FALSE) -> 0 | G4: =AVERAGE(B4:F4) -> 0.8 | H4: =IF(G4>=60%,"pay","don't pay") -> pay
A5: Abrah supermarket | B5: 1 | C5: 0.4 | D5: 1 | E5: 1 | F5: =VLOOKUP(A:A,'SOS VS SOM'!A:E,4,FALSE) -> 0 | G5: =AVERAGE(B5:F5) -> 0.68 | H5: =IF(G5>=60%,"pay","don't pay") -> pay
A6: Active supermarket | B6: 1 | C6: 1 | D6: 1 | E6: 1 | F6: =VLOOKUP(A:A,'SOS VS SOM'!A:E,4,FALSE) -> 0 | G6: =AVERAGE(B6:F6) -> 0.8 | H6: =IF(G6>=60%,"pay","don't pay") -> pay
A7: Apple Door To Door Supermarket | B7: 1 | C7: 0.45454545 | D7: 0.85925926 | E7: 1 | F7: =VLOOKUP(A:A,'SOS VS SOM'!A:E,4,FALSE) -> 0 | G7: =AVERAGE(B7:F7) -> 0.66276094 | H7: =IF(G7>=60%,"pay","don't pay") -> pay
A8: Bam Shopping Centre | B8: 0 | C8: 0.4 | D8: 1 | E8: 1 | F8: =VLOOKUP(A:A,'SOS VS SOM'!A:E,4,FALSE) -> 1 | G8: =AVERAGE(B8:F8) -> 0.68 | H8: =IF(G8>=60%,"pay","don't pay") -> pay
A9: Bea Mart (U) Ltd | B9: 1 | C9: 0.4 | D9: 1 | E9: 1 | F9: =VLOOKUP(A:A,'SOS VS SOM'!A:E,4,FALSE) -> 1 | G9: =AVERAGE(B9:F9) -> 0.88 | H9: =IF(G9>=60%,"pay","don't pay") -> pay
A10: Benco Liner Supermarket Ltd | B10: 1 | C10: 1 | D10: 1 | E10: 1 | F10: =VLOOKUP(A:A,'SOS VS SOM'!A:E,4,FALSE) -> 0 | G10: =AVERAGE(B10:F10) -> 0.8 | H10: =IF(G10>=60%,"pay","don't pay") -> pay
A11: Bengel | B11: 1 | C11: 0.63636364 | D11: 1 | E11: 1 | F11: =VLOOKUP(A:A,'SOS VS SOM'!A:E,4,FALSE) -> 1 | G11: =AVERAGE(B11:F11) -> 0.92727273 | H11: =IF(G11>=60%,"pay","don't pay") -> pay
A12: Best Buy Bukoto | B12: 1 | C12: 0.85 | D12: 0.9962963 | E12: 1 | F12: =VLOOKUP(A:A,'SOS VS SOM'!A:E,4,FALSE) -> 0 | G12: =AVERAGE(B12:F12) -> 0.76925926 | H12: =IF(G12>=60%,"pay","don't pay") -> pay
A13: CAC KYANJA | B13: 1 | C13: 0.55 | D13: 0.97083333 | E13: 1 | F13: =VLOOKUP(A:A,'SOS VS SOM'!A:E,4,FALSE) -> 0 | G13: =AVERAGE(B13:F13) -> 0.70416667 | H13: =IF(G13>=60%,"pay","don't pay") -> pay
A14: Capital Shoppers Garden City | B14: 0 | C14: 0.22222222 | D14: 0.94153846 | E14: 1 | F14: =VLOOKUP(A:A,'SOS VS SOM'!A:E,4,FALSE) -> 0 | G14: =AVERAGE(B14:F14) -> 0.43275214 | H14: =IF(G14>=60%,"pay","don't pay") -> don't pay
... A29: City Joy Kitintale | B29: 1 | C29: 0.9 | D29: 1 | E29: 1 | F29: =VLOOKUP(A:A,'SOS VS SOM'!A:E,4,FALSE) -> 0 | G29: =AVERAGE(B29:F29) -> 0.78 | H29: =IF(G29>=60%,"pay","don't pay") -> pay
A30: City Joy Kitintale | B30: 1 | C30: 0.4 | D30: 1 | E30: 1 | F30: 0 | G30: =AVERAGE(B30:F30) -> 0.68 | H30: =IF(G30>=60%,"pay","don't pay") -> pay
A31: City Joy Mbuya | B31: 1 | C31: 0.64 | D31: 0.96666667 | E31: 1 | F31: =VLOOKUP(A:A,'SOS VS SOM'!A:E,4,FALSE) -> 0 | G31: =AVERAGE(B31:F31) -> 0.72133333 | H31: =IF(G31>=60%,"pay","don't pay") -> pay
A32: City joy supermarket Kireka | B32: 1 | C32: 0.4 | D32: 0.97666667 | E32: 1 | F32: =VLOOKUP(A:A,'SOS VS SOM'!A:E,4,FALSE) -> 0 | G32: =AVERAGE(B32:F32) -> 0.67533333 | H32: =IF(G32>=60%,"pay","don't pay") -> pay
A33: City Shoppers Supermarket | B33: 1 | C33: 1 | D33: 0.8047619 | E33: 1 | F33: =VLOOKUP(A:A,'SOS VS SOM'!A:E,4,FALSE) -> 0 | G33: =AVERAGE(B33:F33) -> 0.76095238 | H33: =IF(G33>=60%,"pay","don't pay") -> pay
A34: Costco | B34: 0 | C34: 0.4 | D34: 1 | E34: 1 | F34: =VLOOKUP(A:A,'SOS VS SOM'!A:E,4,FALSE) -> 0 | G34: =AVERAGE(B34:F34) -> 0.48 | H34: =IF(G34>=60%,"pay","don't pay") -> don't pay
A35: Crane Shoppers | B35: 1 | C35: 0.55 | D35: 1 | E35: 1 | F35: =VLOOKUP(A:A,'SOS VS SOM'!A:E,4,FALSE) -> 0 | G35: =AVERAGE(B35:F35) -> 0.71 | H35: =IF(G35>=60%,"pay","don't pay") -> pay
A36: Crown Stores Sonde | B36: 1 | C36: 0.44444444 | D36: 0.82380952 | E36: 1 | F36: =VLOOKUP(A:A,'SOS VS SOM'!A:E,4,FALSE) -> 0 | G36: =AVERAGE(B36:F36) -> 0.65365079 | H36: =IF(G36>=60%,"pay","don't pay") -> pay
A37: Cynibel General Trading Limited (B | B37: 1 | C37: 1 | D37: 0.99342105 | E37: 1 | F37: =VLOOKUP(A:A,'SOS VS SOM'!A:E,4,FALSE) -> 0 | G37: =AVERAGE(B37:F37) -> 0.79868421 | H37: =IF(G37>=60%,"pay","don't pay") -> pay
A38: Cynibel General Trading Ltd ( Lweza | B38: 0 | C38: 0.88888889 | D38: 1 | E38: 1 | F38: =VLOOKUP(A:A,'SOS VS SOM'!A:E,4,FALSE) -> 0 | G38: =AVERAGE(B38:F38) -> 0.57777778 | H38: =IF(G38>=60%,"pay","don't pay") -> don't pay
A39: Cynibel Kiwatule | B39: 1 | C39: 0.64705882 | D39: 0.96666667 | E39: 1 | F39: =VLOOKUP(A:A,'SOS VS SOM'!A:E,4,FALSE) -> 0 | G39: =AVERAGE(B39:F39) -> 0.7227451 | H39: =IF(G39>=60%,"pay","don't pay") -> pay
A40: Cynibel Super Market | B40: 1 | C40: 1 | D40: 0.99885584 | E40: 1 | F40: =VLOOKUP(A:A,'SOS VS SOM'!A:E,4,FALSE) -> 0 | G40: =AVERAGE(B40:F40) -> 0.79977117 | H40: =IF(G40>=60%,"pay","don't pay") -> pay
A41: Day Day life supermarket | B41: 1 | C41: 0.4 | D41: 1 | E41: 1 | F41: =VLOOKUP(A:A,'SOS VS SOM'!A:E,4,FALSE) -> 0 | G41: =AVERAGE(B41:F41) -> 0.68 | H41: =IF(G41>=60%,"pay","don't pay") -> pay
A42: Day To Day Uganda Limited | B42: 1 | C42: 0.4 | D42: 0.9122807 | E42: 1 | F42: =VLOOKUP(A:A,'SOS VS SOM'!A:E,4,FALSE) -> 0 | G42: =AVERAGE(B42:F42) -> 0.66245614 | H42: =IF(G42>=60%,"pay","don't pay") -> pay
... A46: Dine and Save | B46: 1 | C46: 1 | D46: 0.99583333 | E46: 1 | F46: =VLOOKUP(A:A,'SOS VS SOM'!A:E,4,FALSE) -> 0 | G46: =AVERAGE(B46:F46) -> 0.79916667 | H46: =IF(G46>=60%,"pay","don't pay") -> pay
A47: Dine And Save Supermarket | B47: 1 | C47: 1 | D47: 0.96666667 | E47: 1 | F47: 0 | G47: =AVERAGE(B47:F47) -> 0.79333333 | H47: =IF(G47>=60%,"pay","don't pay") -> pay
A48: Ecomart BUNGA | B48: 1 | C48: 1 | D48: 1 | E48: 1 | F48: =VLOOKUP(A:A,'SOS VS SOM'!A:E,4,FALSE) -> 0 | G48: =AVERAGE(B48:F48) -> 0.8 | H48: =IF(G48>=60%,"pay","don't pay") -> pay
A49: Ecomart Kisaasi | B49: 0 | C49: 1 | D49: 1 | E49: 1 | F49: =VLOOKUP(A:A,'SOS VS SOM'!A:E,4,FALSE) -> 0 | G49: =AVERAGE(B49:F49) -> 0.6 | H49: =IF(G49>=60%,"pay","don't pay") -> pay
A50: Ecomart Kiwatule | B50: 0 | C50: 1 | D50: 0.97235023 | E50: 1 | F50: =VLOOKUP(A:A,'SOS VS SOM'!A:E,4,FALSE) -> 0 | G50: =AVERAGE(B50:F50) -> 0.59447005 | H50: =IF(G50>=60%,"pay","don't pay") -> don't pay
A51: Ecomart Seguku | B51: 1 | C51: 1 | D51: 0.99108138 | E51: 1 | F51: =VLOOKUP(A:A,'SOS VS SOM'!A:E,4,FALSE) -> 0 | G51: =AVERAGE(B51:F51) -> 0.79821628 | H51: =IF(G51>=60%,"pay","don't pay") -> pay
A52: Embassy supermarket LUBOWA | B52: 0 | C52: 1 | D52: 0.97407407 | E52: 1 | F52: =VLOOKUP(A:A,'SOS VS SOM'!A:E,4,FALSE) -> 0 | G52: =AVERAGE(B52:F52) -> 0.59481481 | H52: =IF(G52>=60%,"pay","don't pay") -> don't pay
A53: Equity Shoppers Supermarket | B53: 1 | C53: 1 | D53: 0.96666667 | E53: 1 | F53: =VLOOKUP(A:A,'SOS VS SOM'!A:E,4,FALSE) -> 1 | G53: =AVERAGE(B53:F53) -> 0.99333333 | H53: =IF(G53>=60%,"pay","don't pay") -> pay
A54: Fabulous Freeman | B54: 0 | C54: 0.59090909 | D54: 1 | E54: 1 | F54: 0 | G54: =AVERAGE(B54:F54) -> 0.51818182 | H54: =IF(G54>=60%,"pay","don't pay") -> don't pay
A55: Fabulous Freeman Supermarket | B55: 0 | C55: 0.4 | D55: 1 | E55: 1 | F55: =VLOOKUP(A:A,'SOS VS SOM'!A:E,4,FALSE) -> 1 | G55: =AVERAGE(B55:F55) -> 0.68 | H55: =IF(G55>=60%,"pay","don't pay") -> pay
A56: Family Fresh (Eco Gas) | B56: 0 | C56: 0.4 | D56: 0.98666667 | E56: 1 | F56: =VLOOKUP(A:A,'SOS VS SOM'!A:E,4,FALSE) -> 0 | G56: =AVERAGE(B56:F56) -> 0.47733333 | H56: =IF(G56>=60%,"pay","don't pay") -> don't pay
A57: Fraine Gayaza Road | B57: 0 | C57: 0.4 | D57: 1 | E57: 1 | F57: =VLOOKUP(A:A,'SOS VS SOM'!A:E,4,FALSE) -> 0 | G57: =AVERAGE(B57:F57) -> 0.48 | H57: =IF(G57>=60%,"pay","don't pay") -> don't pay
A58: Fraine Kansanga | B58: 1 | C58: 0.4 | D58: 1 | E58: 1 | F58: =VLOOKUP(A:A,'SOS VS SOM'!A:E,4,FALSE) -> 0 | G58: =AVERAGE(B58:F58) -> 0.68 | H58: =IF(G58>=60%,"pay","don't pay") -> pay
A59: Fraine Kigoowa | B59: 1 | C59: 1 | D59: 1 | E59: 1 | F59: =VLOOKUP(A:A,'SOS VS SOM'!A:E,4,FALSE) -> 0 | G59: =AVERAGE(B59:F59) -> 0.8 | H59: =IF(G59>=60%,"pay","don't pay") -> pay
A60: Fraine Kira | B60: 1 | C60: 1 | D60: 1 | E60: 1 | F60: =VLOOKUP(A:A,'SOS VS SOM'!A:E,4,FALSE) -> 0 | G60: =AVERAGE(B60:F60) -> 0.8 | H60: =IF(G60>=60%,"pay","don't pay") -> pay
A61: Fraine Ntinda | B61: 1 | C61: 1 | D61: 1 | E61: 1 | F61: =VLOOKUP(A:A,'SOS VS SOM'!A:E,4,FALSE) -> 1 | G61: =AVERAGE(B61:F61) -> 1 | H61: =IF(G61>=60%,"pay","don't pay") -> pay
A62: Fresco Supermarket | B62: 1 | C62: 0.85 | D62: 1 | E62: 1 | F62: =VLOOKUP(A:A,'SOS VS SOM'!A:E,4,FALSE) -> 0 | G62: =AVERAGE(B62:F62) -> 0.77 | H62: =IF(G62>=60%,"pay","don't pay") -> pay
A63: Gevas supermarket | B63: 0 | C63: 1 | D63: 0.98888889 | E63: 1 | F63: =VLOOKUP(A:A,'SOS VS SOM'!A:E,4,FALSE) -> 1 | G63: =AVERAGE(B63:F63) -> 0.79777778 | H63: =IF(G63>=60%,"pay","don't pay") -> pay
A64: Gift plus tororo | B64: 1 | C64: 1 | D64: 0.93333333 | E64: 1 | F64: =VLOOKUP(A:A,'SOS VS SOM'!A:E,4,FALSE) -> 0 | G64: =AVERAGE(B64:F64) -> 0.78666667 | H64: =IF(G64>=60%,"pay","don't pay") -> pay
A65: Gleam supermarket | B65: 1 | C65: 0.8 | D65: 1 | E65: 1 | F65: =VLOOKUP(A:A,'SOS VS SOM'!A:E,4,FALSE) -> 0 | G65: =AVERAGE(B65:F65) -> 0.76 | H65: =IF(G65>=60%,"pay","don't pay") -> pay
A66: Global Naalya | B66: 1 | C66: 0.77777778 | D66: 0.99824561 | E66: 1 | F66: 0 | G66: =AVERAGE(B66:F66) -> 0.75520468 | H66: =IF(G66>=60%,"pay","don't pay") -> pay
A67: Goalman Enterprises Limited | B67: 1 | C67: 0.77777778 | D67: 1 | E67: 1 | F67: =VLOOKUP(A:A,'SOS VS SOM'!A:E,4,FALSE) -> 1 | G67: =AVERAGE(B67:F67) -> 0.95555556 | H67: =IF(G67>=60%,"pay","don't pay") -> pay
A68: Golf Supermarket | B68: 0 | C68: 0.4 | D68: 1 | E68: 1 | F68: =VLOOKUP(A:A,'SOS VS SOM'!A:E,4,FALSE) -> 0 | G68: =AVERAGE(B68:F68) -> 0.48 | H68: =IF(G68>=60%,"pay","don't pay") -> don't pay
A69: Hajji &#38 Hajji Smkt | B69: 1 | C69: 1 | D69: 1 | E69: 0 | F69: =VLOOKUP(A:A,'SOS VS SOM'!A:E,4,FALSE) -> 0 | G69: =AVERAGE(B69:F69) -> 0.6 | H69: =IF(G69>=60%,"pay","don't pay") -> pay
A70: Italian mart | B70: 1 | C70: 1 | D70: 0.94358974 | E70: 1 | F70: =VLOOKUP(A:A,'SOS VS SOM'!A:E,4,FALSE) -> 0 | G70: =AVERAGE(B70:F70) -> 0.78871795 | H70: =IF(G70>=60%,"pay","don't pay") -> pay
A71: Jazz | B71: 1 | C71: 0.44444444 | D71: 1 | E71: 1 | F71: =VLOOKUP(A:A,'SOS VS SOM'!A:E,4,FALSE) -> 0 | G71: =AVERAGE(B71:F71) -> 0.68888889 | H71: =IF(G71>=60%,"pay","don't pay") -> pay
A72: JedMart shoppers | B72: 1 | C72: 0.4 | D72: 1 | E72: 1 | F72: =VLOOKUP(A:A,'SOS VS SOM'!A:E,4,FALSE) -> 0 | G72: =AVERAGE(B72:F72) -> 0.68 | H72: =IF(G72>=60%,"pay","don't pay") -> pay
A73: Jtee Supermarket | B73: 0 | C73: 0.72727273 | D73: 0.94583333 | E73: 1 | F73: =VLOOKUP(A:A,'SOS VS SOM'!A:E,4,FALSE) -> 0 | G73: =AVERAGE(B73:F73) -> 0.53462121 | H73: =IF(G73>=60%,"pay","don't pay") -> don't pay
A74: Kabu Supermarket | B74: 1 | C74: 1 | D74: 0.96666667 | E74: 1 | F74: =VLOOKUP(A:A,'SOS VS SOM'!A:E,4,FALSE) -> 0 | G74: =AVERAGE(B74:F74) -> 0.79333333 | H74: =IF(G74>=60%,"pay","don't pay") -> pay
A75: KENJOY ENTERPRISES LIMITED (stella) | B75: 1 | C75: 0.4 | D75: 0.98120301 | E75: 1 | F75: =VLOOKUP(A:A,'SOS VS SOM'!A:E,4,FALSE) -> 0 | G75: =AVERAGE(B75:F75) -> 0.6762406 | H75: =IF(G75>=60%,"pay","don't pay") -> pay
A76: Kenjoy Nansana | B76: 1 | C76: 0.44444444 | D76: 0.96808511 | E76: 1 | F76: =VLOOKUP(A:A,'SOS VS SOM'!A:E,4,FALSE) -> 0 | G76: =AVERAGE(B76:F76) -> 0.68250591 | H76: =IF(G76>=60%,"pay","don't pay") -> pay
A77: Khush Impex | B77: 1 | C77: 1 | D77: 0.93333333 | E77: 1 | F77: =VLOOKUP(A:A,'SOS VS SOM'!A:E,4,FALSE) -> 1 | G77: =AVERAGE(B77:F77) -> 0.98666667 | H77: =IF(G77>=60%,"pay","don't pay") -> pay
A78: Kirimi Supermarket | B78: 1 | C78: 0.4 | D78: 0.93628809 | E78: 1 | F78: =VLOOKUP(A:A,'SOS VS SOM'!A:E,4,FALSE) -> 0 | G78: =AVERAGE(B78:F78) -> 0.66725762 | H78: =IF(G78>=60%,"pay","don't pay") -> pay
... A82: Lexor mart kabusu | B82: 1 | C82: 0.4 | D82: 0.91212121 | E82: 1 | F82: =VLOOKUP(A:A,'SOS VS SOM'!A:E,4,FALSE) -> 0 | G82: =AVERAGE(B82:F82) -> 0.66242424 | H82: =IF(G82>=60%,"pay","don't pay") -> pay
A83: Lucky Star Supermarket | B83: 1 | C83: 0.2 | D83: 0.96666667 | E83: 1 | F83: 0 | G83: =AVERAGE(B83:F83) -> 0.63333333 | H83: =IF(G83>=60%,"pay","don't pay") -> pay
A84: Maama Shoppers Centre | B84: 1 | C84: 0.4 | D84: 0.81904762 | E84: 1 | F84: =VLOOKUP(A:A,'SOS VS SOM'!A:E,4,FALSE) -> 0 | G84: =AVERAGE(B84:F84) -> 0.64380952 | H84: =IF(G84>=60%,"pay","don't pay") -> pay
A85: Maama Shoppers Main | B85: 1 | C85: 0.6 | D85: 0.93333333 | E85: 1 | F85: =VLOOKUP(A:A,'SOS VS SOM'!A:E,4,FALSE) -> 0 | G85: =AVERAGE(B85:F85) -> 0.70666667 | H85: =IF(G85>=60%,"pay","don't pay") -> pay
A86: Makhani Supermarket | B86: 1 | C86: 0.4 | D86: 0.82 | E86: 1 | F86: =VLOOKUP(A:A,'SOS VS SOM'!A:E,4,FALSE) -> 0 | G86: =AVERAGE(B86:F86) -> 0.644 | H86: =IF(G86>=60%,"pay","don't pay") -> pay
A87: Marianah Supermarket | B87: 0 | C87: 0.55555556 | D87: 1 | E87: 1 | F87: =VLOOKUP(A:A,'SOS VS SOM'!A:E,4,FALSE) -> 0 | G87: =AVERAGE(B87:F87) -> 0.51111111 | H87: =IF(G87>=60%,"pay","don't pay") -> don't pay
A88: Masaka No 1 Supermarket | B88: 1 | C88: 0.4 | D88: 0.99583333 | E88: 1 | F88: 0 | G88: =AVERAGE(B88:F88) -> 0.67916667 | H88: =IF(G88>=60%,"pay","don't pay") -> pay
A89: Masters Gayaza | B89: 0 | C89: 1 | D89: 1 | E89: 1 | F89: =VLOOKUP(A:A,'SOS VS SOM'!A:E,4,FALSE) -> 1 | G89: =AVERAGE(B89:F89) -> 0.8 | H89: =IF(G89>=60%,"pay","don't pay") -> pay
A90: Masters Namanve Supermarket | B90: 1 | C90: 1 | D90: 0.94549763 | E90: 1 | F90: =VLOOKUP(A:A,'SOS VS SOM'!A:E,4,FALSE) -> 0 | G90: =AVERAGE(B90:F90) -> 0.78909953 | H90: =IF(G90>=60%,"pay","don't pay") -> pay
A91: Masters Ntinda | B91: 1 | C91: 0.55 | D91: 1 | E91: 1 | F91: =VLOOKUP(A:A,'SOS VS SOM'!A:E,4,FALSE) -> 0 | G91: =AVERAGE(B91:F91) -> 0.71 | H91: =IF(G91>=60%,"pay","don't pay") -> pay
A92: Mega Standard Supermarket Lweza | B92: 0 | C92: 1 | D92: 1 | E92: 1 | F92: =VLOOKUP(A:A,'SOS VS SOM'!A:E,4,FALSE) -> 0 | G92: =AVERAGE(B92:F92) -> 0.6 | H92: =IF(G92>=60%,"pay","don't pay") -> pay
A93: Miami supermarket | B93: 0 | C93: 1 | D93: 0.76111111 | E93: 0.66666667 | F93: =VLOOKUP(A:A,'SOS VS SOM'!A:E,4,FALSE) -> 1 | G93: =AVERAGE(B93:F93) -> 0.68555556 | H93: =IF(G93>=60%,"pay","don't pay") -> pay
A94: Midway Supermarket | B94: 0 | C94: 0.45454545 | D94: 0.96333333 | E94: 1 | F94: =VLOOKUP(A:A,'SOS VS SOM'!A:E,4,FALSE) -> 0 | G94: =AVERAGE(B94:F94) -> 0.48357576 | H94: =IF(G94>=60%,"pay","don't pay") -> don't pay
A95: MILLENIUM 2000 | B95: 1 | C95: 0.55555556 | D95: 0.98095238 | E95: 1 | F95: =VLOOKUP(A:A,'SOS VS SOM'!A:E,4,FALSE) -> 0 | G95: =AVERAGE(B95:F95) -> 0.70730159 | H95: =IF(G95>=60%,"pay","don't pay") -> pay
A96: Mirembe shoppers | B96: 1 | C96: 0.6 | D96: 0.97333333 | E96: 0.5 | F96: 0 | G96: =AVERAGE(B96:F96) -> 0.61466667 | H96: =IF(G96>=60%,"pay","don't pay") -> pay
A97: Muzirango And Sons Ltd | B97: 1 | C97: 0.44444444 | D97: 0.95185185 | E97: 1 | F97: =VLOOKUP(A:A,'SOS VS SOM'!A:E,4,FALSE) -> 0 | G97: =AVERAGE(B97:F97) -> 0.67925926 | H97: =IF(G97>=60%,"pay","don't pay") -> pay
A98: Nadia Supermarket | B98: 1 | C98: 0.4 | D98: 1 | E98: 1 | F98: =VLOOKUP(A:A,'SOS VS SOM'!A:E,4,FALSE) -> 0 | G98: =AVERAGE(B98:F98) -> 0.68 | H98: =IF(G98>=60%,"pay","don't pay") -> pay
A99: Navya Impex Limited | B99: 1 | C99: 1 | D99: 1 | E99: 1 | F99: =VLOOKUP(A:A,'SOS VS SOM'!A:E,4,FALSE) -> 1 | G99: =AVERAGE(B99:F99) -> 1 | H99: =IF(G99>=60%,"pay","don't pay") -> pay
A100: New Abrah Supermarket | B100: 1 | C100: 1 | D100: 1 | E100: 1 | F100: =VLOOKUP(A:A,'SOS VS SOM'!A:E,4,FALSE) -> 0 | G100: =AVERAGE(B100:F100) -> 0.8 | H100: =IF(G100>=60%,"pay","don't pay") -> pay
A101: New Welcome Shoppers | B101: 1 | C101: 1 | D101: 1 | E101: 1 | F101: =VLOOKUP(A:A,'SOS VS SOM'!A:E,4,FALSE) -> 0 | G101: =AVERAGE(B101:F101) -> 0.8 | H101: =IF(G101>=60%,"pay","don't pay") -> pay
A102: Nile Delight 2 | B102: 1 | C102: 0.7 | D102: 0.96666667 | E102: 1 | F102: =VLOOKUP(A:A,'SOS VS SOM'!A:E,4,FALSE) -> 0 | G102: =AVERAGE(B102:F102) -> 0.73333333 | H102: =IF(G102>=60%,"pay","don't pay") -> pay
A103: OK supermarket Ltd | B103: 1 | C103: 0.4 | D103: 0.81666667 | E103: 1 | F103: =VLOOKUP(A:A,'SOS VS SOM'!A:E,4,FALSE) -> 0 | G103: =AVERAGE(B103:F103) -> 0.64333333 | H103: =IF(G103>=60%,"pay","don't pay") -> pay
A104: Olita Investments Ltd | B104: 1 | C104: 0.55 | D104: 1 | E104: 1 | F104: =VLOOKUP(A:A,'SOS VS SOM'!A:E,4,FALSE) -> 0 | G104: =AVERAGE(B104:F104) -> 0.71 | H104: =IF(G104>=60%,"pay","don't pay") -> pay
A105: Om Supermarket Limited | B105: 1 | C105: 1 | D105: 1 | E105: 1 | F105: =VLOOKUP(A:A,'SOS VS SOM'!A:E,4,FALSE) -> 1 | G105: =AVERAGE(B105:F105) -> 1 | H105: =IF(G105>=60%,"pay","don't pay") -> pay
A106: Our Global Enterprises | B106: 1 | C106: 0.44444444 | D106: 0.53888889 | E106: 1 | F106: =VLOOKUP(A:A,'SOS VS SOM'!A:E,4,FALSE) -> 0 | G106: =AVERAGE(B106:F106) -> 0.59666667 | H106: =IF(G106>=60%,"pay","don't pay") -> don't pay
A107: Padova 1 | B107: 1 | C107: 0.75 | D107: 1 | E107: 1 | F107: =VLOOKUP(A:A,'SOS VS SOM'!A:E,4,FALSE) -> 0 | G107: =AVERAGE(B107:F107) -> 0.75 | H107: =IF(G107>=60%,"pay","don't pay") -> pay
A108: Padova Namasuba Stage | B108: 1 | C108: 0.8 | D108: 1 | E108: 1 | F108: 0 | G108: =AVERAGE(B108:F108) -> 0.76 | H108: =IF(G108>=60%,"pay","don't pay") -> pay
A109: Panama Supermarket | B109: 1 | C109: 0.77777778 | D109: 0.98148148 | E109: 1 | F109: 0 | G109: =AVERAGE(B109:F109) -> 0.75185185 | H109: =IF(G109>=60%,"pay","don't pay") -> pay
A110: Paradise Supermarket | B110: 0 | C110: 0.6 | D110: 0.94166667 | E110: 1 | F110: 0 | G110: =AVERAGE(B110:F110) -> 0.50833333 | H110: =IF(G110>=60%,"pay","don't pay") -> don't pay
A111: Paris Corner Supermarket | B111: 1 | C111: 1 | D111: 0.94912281 | E111: 1 | F111: =VLOOKUP(A:A,'SOS VS SOM'!A:E,4,FALSE) -> 1 | G111: =AVERAGE(B111:F111) -> 0.98982456 | H111: =IF(G111>=60%,"pay","don't pay") -> pay
A112: Pearl Shopping Center Limited | B112: 0 | C112: 1 | D112: 0.94736842 | E112: 1 | F112: =VLOOKUP(A:A,'SOS VS SOM'!A:E,4,FALSE) -> 0 | G112: =AVERAGE(B112:F112) -> 0.58947368 | H112: =IF(G112>=60%,"pay","don't pay") -> don't pay
A113: Peoples Supermarket 0703932011 | B113: 0 | C113: 0 | D113: 0.97857143 | E113: 0 | F113: =VLOOKUP(A:A,'SOS VS SOM'!A:E,4,FALSE) -> 0 | G113: =AVERAGE(B113:F113) -> 0.19571429 | H113: =IF(G113>=60%,"pay","don't pay") -> don't pay
A114: Poonam Enterprises Supermkt | B114: 0 | C114: 0.7 | D114: 1 | E114: 1 | F114: =VLOOKUP(A:A,'SOS VS SOM'!A:E,4,FALSE) -> 0 | G114: =AVERAGE(B114:F114) -> 0.54 | H114: =IF(G114>=60%,"pay","don't pay") -> don't pay
A115: Quality Martin Road | B115: 0 | C115: 0.44444444 | D115: 0.92307692 | E115: 1 | F115: =VLOOKUP(A:A,'SOS VS SOM'!A:E,4,FALSE) -> 0 | G115: =AVERAGE(B115:F115) -> 0.47350427 | H115: =IF(G115>=60%,"pay","don't pay") -> don't pay
A116: Quality Supermarket - Kitende | B116: 0 | C116: 0.4 | D116: 0.92307692 | E116: 1 | F116: =VLOOKUP(A:A,'SOS VS SOM'!A:E,4,FALSE) -> 0 | G116: =AVERAGE(B116:F116) -> 0.46461538 | H116: =IF(G116>=60%,"pay","don't pay") -> don't pay
A117: Quality Supermarket - Lubowa. | B117: 0 | C117: 0.44444444 | D117: 0.92601726 | E117: 1 | F117: =VLOOKUP(A:A,'SOS VS SOM'!A:E,4,FALSE) -> 0 | G117: =AVERAGE(B117:F117) -> 0.47409234 | H117: =IF(G117>=60%,"pay","don't pay") -> don't pay
A118: Quality Supermarket Naalya | B118: 0 | C118: 0.4 | D118: 0.85714286 | E118: 1 | F118: =VLOOKUP(A:A,'SOS VS SOM'!A:E,4,FALSE) -> 0 | G118: =AVERAGE(B118:F118) -> 0.45142857 | H118: =IF(G118>=60%,"pay","don't pay") -> don't pay
A119: Rab Lines Trading Co. | B119: 1 | C119: 0.4 | D119: 0.87435897 | E119: 1 | F119: =VLOOKUP(A:A,'SOS VS SOM'!A:E,4,FALSE) -> 1 | G119: =AVERAGE(B119:F119) -> 0.85487179 | H119: =IF(G119>=60%,"pay","don't pay") -> pay
A120: Rehoboth supermarket | B120: 1 | C120: 0.88888889 | D120: 1 | E120: 1 | F120: =VLOOKUP(A:A,'SOS VS SOM'!A:E,4,FALSE) -> 1 | G120: =AVERAGE(B120:F120) -> 0.97777778 | H120: =IF(G120>=60%,"pay","don't pay") -> pay
A121: Republic S/M | B121: 1 | C121: 0.66666667 | D121: 1 | E121: 1 | F121: =VLOOKUP(A:A,'SOS VS SOM'!A:E,4,FALSE) -> 0 | G121: =AVERAGE(B121:F121) -> 0.73333333 | H121: =IF(G121>=60%,"pay","don't pay") -> pay
...

Sheet SOS VS SOM
A1: OUTLETS | B1: % SOS | C1: %SOM | D1: SOS VS SOM | E1: Pay status
A2: Apple Door To Door Supermarket | B2: 0.29525 | C2: 0.44153846 | D2: 0 | E2: =IF(Table1[[#This Row],[SOS VS SOM]]=100%,"Pay","Don't pay") -> Don't pay
A3: Bea Mart (U) Ltd | B3: 0.40875 | C3: 0.40133333 | D3: 1 | E3: =IF(Table1[[#This Row],[SOS VS SOM]]=100%,"Pay","Don't pay") -> Pay
A4: Benco Liner Supermarket Ltd | B4: 0.3459375 | C4: 0.40083333 | D4: 0 | E4: =IF(Table1[[#This Row],[SOS VS SOM]]=100%,"Pay","Don't pay") -> Don't pay
A5: Capital Shoppers Garden City | B5: 0.19354167 | C5: 0.33928571 | D5: 0 | E5: =IF(Table1[[#This Row],[SOS VS SOM]]=100%,"Pay","Don't pay") -> Don't pay
A6: Capital Shoppers Supermarket - Ntinda | B6: 0.2625 | C6: 0.432 | D6: 0 | E6: =IF(Table1[[#This Row],[SOS VS SOM]]=100%,"Pay","Don't pay") -> Don't pay
A7: Carrefour Uganda - Acacia Mall | B7: 0.18895833 | C7: 0.29933333 | D7: 0 | E7: =IF(Table1[[#This Row],[SOS VS SOM]]=100%,"Pay","Don't pay") -> Don't pay
A8: Carrefour Uganda - Naalya | B8: 0.22 | C8: 0.305 | D8: 0 | E8: =IF(Table1[[#This Row],[SOS VS SOM]]=100%,"Pay","Don't pay") -> Don't pay
A9: Carrefour Victoria Mall | B9: 0.19 | C9: 0.28857143 | D9: 0 | E9: =IF(Table1[[#This Row],[SOS VS SOM]]=100%,"Pay","Don't pay") -> Don't pay
A10: Carrefour village mall | B10: 0.2275 | C10: 0.366 | D10: 0 | E10: =IF(Table1[[#This Row],[SOS VS SOM]]=100%,"Pay","Don't pay") -> Don't pay
A11: City joy supermarket Kireka | B11: 0.33625 | C11: 0.49307692 | D11: 0 | E11: =IF(Table1[[#This Row],[SOS VS SOM]]=100%,"Pay","Don't pay") -> Don't pay
A12: Cynibel General Trading Limited (B | B12: 0.220625 | C12: 0.30384615 | D12: 0 | E12: =IF(Table1[[#This Row],[SOS VS SOM]]=100%,"Pay","Don't pay") -> Don't pay
A13: Cynibel Super Market | B13: 0.304375 | C13: 0.35071429 | D13: 0 | E13: =IF(Table1[[#This Row],[SOS VS SOM]]=100%,"Pay","Don't pay") -> Don't pay
... A141: Dine and Save | B141: 0.31375 | C141: 0.48866667 | D141: 0 | E141: =IF(Table1[[#This Row],[SOS VS SOM]]=100%,"Pay","Don't pay") -> Don't pay

Sheet PVT
A3: Sum of Home care | B3: Column Labels
A4: Row Labels | B4: Center Alignment | C4: NPD | D4: OSA | E4: POSM
A5: 2k shoppers | B5: 1 | C5: 0.77777778 | D5: 1 | E5: 1
A6: Abra Shopping Centre | B6: 1 | C6: 1 | D6: 1 | E6: 1
A7: Abrah supermarket | B7: 1 | C7: 0.4 | D7: 1 | E7: 1
A8: Active supermarket | B8: 1 | C8: 1 | D8: 1 | E8: 1
A9: Apple Door To Door Supermarket | B9: 1 | C9: 0.45454545 | D9: 0.85925926 | E9: 1
A10: Bam Shopping Centre | B10: 0 | C10: 0.4 | D10: 1 | E10: 1
A11: Bea Mart (U) Ltd | B11: 1 | C11: 0.4 | D11: 1 | E11: 1
A12: Benco Liner Supermarket Ltd | B12: 1 | C12: 1 | D12: 1 | E12: 1
A13: Bengel | B13: 1 | C13: 0.63636364 | D13: 1 | E13: 1
A14: Best Buy Bukoto | B14: 1 | C14: 0.85 | D14: 0.9962963 | E14: 1
A15: CAC KYANJA | B15: 1 | C15: 0.55 | D15: 0.97083333 | E15: 1
A16: Capital Shoppers Garden City | B16: 0 | C16: 0.22222222 | D16: 0.94153846 | E16: 1
... A30: China Town Lugogo Mall | B30: 1 | C30: 0.86363636 | D30: 0.96439628 | E30: 1
A31: Citizen supermarket | D31: 1
A32: City Joy Kitintale | B32: 1 | C32: 0.9 | D32: 1 | E32: 1
A33: City Joy Kitintale | B33: 1 | C33: 0.4 | D33: 1 | E33: 1
A34: City Joy Mbuya | B34: 1 | C34: 0.64 | D34: 0.96666667 | E34: 1
A35: City joy supermarket Kireka | B35: 1 | C35: 0.4 | D35: 0.97666667 | E35: 1
A36: City Shoppers Supermarket | B36: 1 | C36: 1 | D36: 0.8047619 | E36: 1
A37: Cobrena supermarket | D37: 0.97037037
A38: Costco | C38: 0.4 | D38: 1 | E38: 1
A39: Crane Shoppers | B39: 1 | C39: 0.55 | D39: 1 | E39: 1
A40: Crown Stores Lubowa | D40: 1
A41: Crown Stores Sonde | B41: 1 | C41: 0.44444444 | D41: 0.82380952 | E41: 1
A42: Cynibel General Trading Limited (B | B42: 1 | C42: 1 | D42: 0.99342105 | E42: 1
A43: Cynibel General Trading Ltd ( Lweza | B43: 0 | C43: 0.88888889 | D43: 1 | E43: 1
A44: Cynibel Kiwatule | B44: 1 | C44: 0.64705882 | D44: 0.96666667 | E44: 1
A45: Cynibel Super Market | B45: 1 | C45: 1 | D45: 0.99885584 | E45: 1
A46: Day Day life supermarket | B46: 1 | C46: 0.4 | D46: 1 | E46: 1
A47: Day To Day Uganda Limited | B47: 1 | C47: 0.4 | D47: 0.9122807 | E47: 1
A48: DE PENTA | B48: 0 | C48: 0.45454545 | D48: 0.43809524 | E48: 1
A49: Deluxe Supermarket | B49: 1 | C49: 0.36363636 | D49: 0.98888889 | E49: 1
A50: Dembe smkt | B50: 1 | C50: 0.86363636 | D50: 1 | E50: 1
A51: Dine and Save | B51: 1 | C51: 1 | D51: 0.99583333 | E51: 1
A52: Dine And Save Supermarket | B52: 1 | C52: 1 | D52: 0.96666667 | E52: 1
... A58: Equity Shoppers Supermarket | B58: 1 | C58: 1 | D58: 0.96666667 | E58: 1
A59: Fabulous Freeman | C59: 0.59090909 | D59: 1 | E59: 1
A60: Fabulous Freeman Supermarket | B60: 0 | C60: 0.4 | D60: 1 | E60: 1
A61: Family Fresh (Eco Gas) | B61: 0 | C61: 0.4 | D61: 0.98666667 | E61: 1
A62: Fraine Gayaza Road | B62: 0 | C62: 0.4 | D62: 1 | E62: 1
A63: Fraine Kansanga | B63: 1 | C63: 0.4 | D63: 1 | E63: 1
A64: Fraine Kigoowa | B64: 1 | C64: 1 | D64: 1 | E64: 1
A65: Fraine Kira | B65: 1 | C65: 1 | D65: 1 | E65: 1
A66: Fraine Ntinda | B66: 1 | C66: 1 | D66: 1 | E66: 1
A67: Frame mart supermarket | D67: 0.95
A68: Freddie mini supermarket | D68: 0.87
A69: Fresco Supermarket | B69: 1 | C69: 0.85 | D69: 1 | E69: 1
A70: Gevas supermarket | B70: 0 | C70: 1 | D70: 0.98888889 | E70: 1
A71: Gift plus tororo | B71: 1 | C71: 1 | D71: 0.93333333 | E71: 1
A72: Gleam supermarket | B72: 1 | C72: 0.8 | D72: 1 | E72: 1
A73: Global Naalya | B73: 1 | C73: 0.77777778 | D73: 0.99824561 | E73: 1
A74: Goalman Enterprises Limited | B74: 1 | C74: 0.77777778 | D74: 1 | E74: 1
A75: Golf Supermarket | B75: 0 | C75: 0.4 | D75: 1 | E75: 1
A76: Hajji &#38 Hajji Smkt | B76: 1 | C76: 1 | D76: 1 | E76: 0
A77: Italian mart | B77: 1 | C77: 1 | D77: 0.94358974 | E77: 1
A78: Jafa supermarket | D78: 0.95555556
A79: Jazz | B79: 1 | C79: 0.44444444 | D79: 1 | E79: 1
A80: JedMart shoppers | B80: 1 | C80: 0.4 | D80: 1 | E80: 1
A81: Jtee Supermarket | B81: 0 | C81: 0.72727273 | D81: 0.94583333 | E81: 1
A82: Kabu Supermarket | B82: 1 | C82: 1 | D82: 0.96666667 | E82: 1
A83: KENJOY ENTERPRISES LIMITED (mengo) | D83: 0.99122807
A84: KENJOY ENTERPRISES LIMITED (stella) | B84: 1 | C84: 0.4 | D84: 0.98120301 | E84: 1
A85: kenjoy mengo | D85: 0.96666667
A86: Kenjoy Nansana | B86: 1 | C86: 0.44444444 | D86: 0.96808511 | E86: 1
A87: Khush Impex | B87: 1 | C87: 1 | D87: 0.93333333 | E87: 1
A88: Kirimi Supermarket | B88: 1 | C88: 0.4 | D88: 0.93628809 | E88: 1
A89: Kwaja 1 | B89: 1 | C89: 0.44444444 | D89: 0.82777778 | E89: 1
A90: Labora | B90: 1 | C90: 1 | D90: 1 | E90: 1
A91: Lebron Smkt | B91: 0 | C91: 0.9 | D91: 0.93181818 | E91: 1
A92: Lexor mart kabusu | B92: 1 | C92: 0.4 | D92: 0.91212121 | E92: 1
A93: Lucky Star Supermarket | B93: 1 | C93: 0.2 | D93: 0.96666667 | E93: 1
A94: Maama Shoppers Centre | B94: 1 | C94: 0.4 | D94: 0.81904762 | E94: 1
A95: Maama Shoppers Main | B95: 1 | C95: 0.6 | D95: 0.93333333 | E95: 1
A96: Makhani Supermarket | B96: 1 | C96: 0.4 | D96: 0.82 | E96: 1
A97: Marianah Supermarket | B97: 0 | C97: 0.55555556 | D97: 1 | E97: 1
... A101: Masters Ntinda | B101: 1 | C101: 0.55 | D101: 1 | E101: 1
A102: mega standard garden city | D102: 0.98076923
A103: Mega Standard Supermarket Lweza | B103: 0 | C103: 1 | D103: 1 | E103: 1
A104: Miami supermarket | B104: 0 | C104: 1 | D104: 0.76111111 | E104: 0.66666667
A105: Midway Supermarket | B105: 0 | C105: 0.45454545 | D105: 0.96333333 | E105: 1
A106: MILLENIUM 2000 | B106: 1 | C106: 0.55555556 | D106: 0.98095238 | E106: 1
A107: Mirembe shoppers | B107: 1 | C107: 0.6 | D107: 0.97333333 | E107: 0.5
A108: Muzirango And Sons Ltd | B108: 1 | C108: 0.44444444 | D108: 0.95185185 | E108: 1
A109: Nadia Supermarket | B109: 1 | C109: 0.4 | D109: 1 | E109: 1
A110: Navya Impex Limited | B110: 1 | C110: 1 | D110: 1 | E110: 1
A111: New Abrah Supermarket | B111: 1 | C111: 1 | D111: 1 | E111: 1
A112: New Welcome Shoppers | B112: 1 | C112: 1 | D112: 1 | E112: 1
A113: Nile Delight 2 | B113: 1 | C113: 0.7 | D113: 0.96666667 | E113: 1
A114: OK supermarket Ltd | B114: 1 | C114: 0.4 | D114: 0.81666667 | E114: 1
... A119: Padova Namasuba Stage | B119: 1 | C119: 0.8 | D119: 1 | E119: 1
A120: Panama kisasi | D120: 1
A121: Panama Supermarket | B121: 1 | C121: 0.77777778 | D121: 0.98148148 | E121: 1
A122: Paradise Supermarket | B122: 0 | C122: 0.6 | D122: 0.94166667 | E122: 1
A123: Paris Corner Supermarket | B123: 1 | C123: 1 | D123: 0.94912281 | E123: 1
A124: Pearl Shopping Center Limited | B124: 0 | C124: 1 | D124: 0.94736842 | E124: 1
A125: Peoples Supermarket 0703932011 | D125: 0.97857143
A126: Poonam Enterprises Supermkt | B126: 0 | C126: 0.7 | D126: 1 | E126: 1
A127: Quality Martin Road | B127: 0 | C127: 0.44444444 | D127: 0.92307692 | E127: 1
...

Sheet RAW DATA
B2: OUTLET NAME | C2: CHANNEL | D2: DISTRIBUTOR | E2: Home care | F2: Personal care | G2: Beauty and well being | H2: Foods | I2: Score | J2: KPI
B3: 2k shoppers | C3: Lmt Account | D3: Dredro Distributors | E3: 1 | F3: 1 | G3: 1 | H3: 1 | I3: 1 | J3: OSA
B4: Abra Shopping Centre | C4: Lmt Account | D4: Qima Ventures Enterprises | E4: 1 | F4: 1 | G4: 1 | H4: 1 | I4: 1 | J4: OSA
B5: Abrah supermarket | C5: Lmt Account | D5: Dredro Distributors | E5: 1 | F5: 1 | G5: 1 | H5: 0.88888889 | I5: 0.97222222 | J5: OSA
B6: Active supermarket | C6: Lmt Account | D6: Gt Trading Limited | E6: 1 | F6: 1 | G6: 1 | H6: 1 | I6: 1 | J6: OSA
B7: Apple Door To Door Supermarket | C7: Lmt Account | D7: Falkan Investments Ltd Mbarara | E7: 0.85925926 | F7: 1 | G7: 1 | H7: 0.64197531 | I7: 0.87530864 | J7: OSA
B8: Bam Shopping Centre | C8: Lmt Account | D8: Qima Ventures Enterprises | E8: 1 | F8: 1 | G8: 1 | H8: 1 | I8: 1 | J8: OSA
B9: Bea Mart (U) Ltd | C9: Lmt Account | D9: Salvo Grima Fortportal | E9: 1 | F9: 1 | G9: 1 | H9: 1 | I9: 1 | J9: OSA
B10: Benco Liner Supermarket Ltd | C10: Lmt Account | D10: Zeripen Investments Limited | E10: 1 | F10: 1 | G10: 1 | H10: 1 | I10: 1 | J10: OSA
B11: Bengel | C11: Lmt Account | D11: Qima Ventures Enterprises | E11: 1 | F11: 1 | G11: 1 | H11: 1 | I11: 1 | J11: OSA
B12: Best Buy Bukoto | C12: Lmt Account | D12: Salvo Grima Kampala | E12: 0.9962963 | F12: 1 | G12: 1 | H12: 1 | I12: 0.99907407 | J12: OSA
B13: CAC KYANJA | C13: Lmt Account | D13: Salvo Grima Kampala | E13: 0.97083333 | F13: 1 | G13: 1 | H13: 1 | I13: 0.99270833 | J13: OSA
B14: Capital Shoppers Garden City | C14: Capital Account | D14: Dhl | E14: 0.94153846 | F14: 1 | G14: 0.96 | H14: 0.98222222 | I14: 0.97094017 | J14: OSA
... B164: Wilsen Supermarket | C164: Lmt Account | D164: Davakam Collections Ltd Kampala | E164: 0.98095238 | F164: 0.98571429 | G164: 0.87662338 | H164: 0.82539683 | I164: 0.91717172 | J164: OSA
B165: 2k shoppers | C165: Lmt Account | D165: Dredro Distributors | E165: 0.77777778 | F165: 1 | I165: 0.88888889 | J165: NPD
B166: Abra Shopping Centre | C166: Lmt Account | D166: Qima Ventures Enterprises | E166: 1 | F166: 1 | I166: 1 | J166: NPD
B167: Abrah supermarket | C167: Lmt Account | D167: Dredro Distributors | E167: 0.4 | F167: 1 | I167: 0.7 | J167: NPD
B168: Active supermarket | C168: Lmt Account | D168: Gt Trading Limited | E168: 1 | F168: 1 | I168: 1 | J168: NPD
B169: Apple Door To Door Supermarket | C169: Lmt Account | D169: Falkan Investments Ltd Mbarara | E169: 0.45454545 | F169: 1 | I169: 0.72727273 | J169: NPD
B170: Bam Shopping Centre | C170: Lmt Account | D170: Qima Ventures Enterprises | E170: 0.4 | F170: 1 | I170: 0.7 | J170: NPD
B171: Bea Mart (U) Ltd | C171: Lmt Account | D171: Salvo Grima Fortportal | E171: 0.4 | F171: 1 | I171: 0.7 | J171: NPD
B172: Benco Liner Supermarket Ltd | C172: Lmt Account | D172: Zeripen Investments Limited | E172: 1 | F172: 1 | I172: 1 | J172: NPD
B173: Bengel | C173: Lmt Account | D173: Qima Ventures Enterprises | E173: 0.63636364 | F173: 1 | I173: 0.81818182 | J173: NPD
B174: Best Buy Bukoto | C174: Lmt Account | D174: Salvo Grima Kampala | E174: 0.85 | F174: 1 | I174: 0.925 | J174: NPD
B175: CAC KYANJA | C175: Lmt Account | D175: Salvo Grima Kampala | E175: 0.55 | F175: 1 | I175: 0.775 | J175: NPD
B176: Capital Shoppers Garden City | C176: Capital Account | D176: Dhl | E176: 0.22222222 | F176: 1 | I176: 0.61111111 | J176: NPD
... B314: Wilsen Supermarket | C314: Lmt Account | D314: Davakam Collections Ltd Kampala | E314: 0.4 | F314: 1 | I314: 0.7 | J314: NPD
B315: 2k shoppers | C315: Lmt Account | D315: Dredro Distributors | E315: 1 | F315: 1 | G315: 1 | H315: 1 | I315: 1 | J315: POSM
B316: Abra Shopping Centre | C316: Lmt Account | D316: Qima Ventures Enterprises | E316: 1 | F316: 1 | G316: 1 | H316: 1 | I316: 1 | J316: POSM
B317: Abrah supermarket | C317: Lmt Account | D317: Dredro Distributors | E317: 1 | F317: 1 | G317: 1 | H317: 1 | I317: 1 | J317: POSM
B318: Active supermarket | C318: Lmt Account | D318: Gt Trading Limited | E318: 1 | F318: 1 | G318: 1 | H318: 1 | I318: 1 | J318: POSM
B319: Apple Door To Door Supermarket | C319: Lmt Account | D319: Falkan Investments Ltd Mbarara | E319: 1 | F319: 1 | G319: 1 | H319: 1 | I319: 1 | J319: POSM
B320: Bam Shopping Centre | C320: Lmt Account | D320: Qima Ventures Enterprises | E320: 1 | F320: 1 | G320: 1 | H320: 1 | I320: 1 | J320: POSM
B321: Bea Mart (U) Ltd | C321: Lmt Account | D321: Salvo Grima Fortportal | E321: 1 | F321: 1 | G321: 1 | H321: 1 | I321: 1 | J321: POSM
B322: Benco Liner Supermarket Ltd | C322: Lmt Account | D322: Zeripen Investments Limited | E322: 1 | F322: 1 | G322: 1 | H322: 1 | I322: 1 | J322: POSM
B323: Bengel | C323: Lmt Account | D323: Qima Ventures Enterprises | E323: 1 | F323: 1 | G323: 1 | H323: 1 | I323: 1 | J323: POSM
B324: Best Buy Bukoto | C324: Lmt Account | D324: Salvo Grima Kampala | E324: 1 | F324: 1 | G324: 1 | H324: 1 | I324: 1 | J324: POSM
B325: CAC KYANJA | C325: Lmt Account | D325: Salvo Grima Kampala | E325: 1 | F325: 1 | G325: 1 | H325: 1 | I325: 1 | J325: POSM
B326: Capital Shoppers Garden City | C326: Capital Account | D326: Dhl | E326: 1 | F326: 1 | G326: 1 | H326: 1 | I326: 1 | J326: POSM
... B464: Wilsen Supermarket | C464: Lmt Account | D464: Davakam Collections Ltd Kampala | E464: 1 | F464: 1 | G464: 1 | H464: 1 | I464: 1 | J464: POSM
B465: 2k shoppers | C465: Lmt Account | D465: Dredro Distributors | E465: 1 | F465: 1 | G465: 1 | H465: 1 | I465: =AVERAGE(E465:H465) -> 1 | J465: Center Alignment
B466: Abra Shopping Centre | C466: Lmt Account | D466: Qima Ventures Enterprises | E466: 1 | F466: 1 | G466: 1 | H466: 1 | I466: =AVERAGE(E466:H466) -> 1 | J466: Center Alignment
B467: Abrah supermarket | C467: Lmt Account | D467: Dredro Distributors | E467: 1 | F467: 1 | G467: 1 | H467: 1 | I467: =AVERAGE(E467:H467) -> 1 | J467: Center Alignment
B468: Active supermarket | C468: Lmt Account | D468: Gt Trading Limited | E468: 1 | F468: 1 | G468: 1 | H468: 1 | I468: =AVERAGE(E468:H468) -> 1 | J468: Center Alignment
B469: Apple Door To Door Supermarket | C469: Lmt Account | D469: Falkan Investments Ltd Mbarara | E469: 1 | F469: 1 | G469: 1 | H469: 1 | I469: =AVERAGE(E469:H469) -> 1 | J469: Center Alignment
B470: Bam Shopping Centre | C470: Lmt Account | D470: Qima Ventures Enterprises | E470: 0 | F470: 1 | G470: 1 | H470: 1 | I470: =AVERAGE(E470:H470) -> 0.75 | J470: Center Alignment
B471: Bea Mart (U) Ltd | C471: Lmt Account | D471: Salvo Grima Fortportal | E471: 1 | F471: 1 | G471: 1 | H471: 0 | I471: =AVERAGE(E471:H471) -> 0.75 | J471: Center Alignment
B472: Benco Liner Supermarket Ltd | C472: Lmt Account | D472: Zeripen Investments Limited | E472: 1 | F472: 1 | G472: 0 | H472: 1 | I472: =AVERAGE(E472:H472) -> 0.75 | J472: Center Alignment
B473: Bengel | C473: Lmt Account | D473: Qima Ventures Enterprises | E473: 1 | F473: 1 | G473: 1 | H473: 1 | I473: =AVERAGE(E473:H473) -> 1 | J473: Center Alignment
B474: Best Buy Bukoto | C474: Lmt Account | D474: Salvo Grima Kampala | E474: 1 | F474: 1 | G474: 1 | H474: 1 | I474: =AVERAGE(E474:H474) -> 1 | J474: Center Alignment
B475: CAC KYANJA | C475: Lmt Account | D475: Salvo Grima Kampala | E475: 1 | F475: 1 | G475: 1 | H475: 1 | I475: =AVERAGE(E475:H475) -> 1 | J475: Center Alignment
B476: Capital Shoppers Garden City | C476: Capital Account | D476: Dhl | E476: 0 | F476: 1 | G476: 1 | H476: 1 | I476: =AVERAGE(E476:H476) -> 0.75 | J476: Center Alignment
... B547: Maama Shoppers Main | C547: Lmt Account | D547: Rabriel Investments Lira | E547: 1 | F547: 1 | G547: 1 | H547: 1 | I547: =AVERAGE(E547:H547) -> 1 | J547: Center Alignment
B548: Makhani Supermarket | C548: Lmt Account | D548: Rabriel Investments Lira | E548: 1 | F548: 1 | G548: 1 | I548: =AVERAGE(E548:H548) -> 1 | J548: Center Alignment
B549: Marianah Supermarket | C549: Lmt Account | D549: Zeripen Investments Limited | E549: 0 | F549: 0 | G549: 0 | H549: 0 | I549: =AVERAGE(E549:H549) -> 0 | J549: Center Alignment
B550: Masaka No 1 Supermarket | C550: Lmt Account | D550: Salvo Grima Masaka | E550: 1 | F550: 1 | G550: 0 | H550: 1 | I550: =AVERAGE(E550:H550) -> 0.75 | J550: Center Alignment
B551: Masters Gayaza | C551: Lmt Account | D551: Davakam Collections Ltd Kampala | E551: 0 | F551: 1 | G551: 1 | H551: 1 | I551: =AVERAGE(E551:H551) -> 0.75 | J551: Center Alignment
B552: Masters Namanve Supermarket | C552: Lmt Account | D552: Mofunds Ltd | E552: 1 | F552: 1 | G552: 1 | H552: 1 | I552: =AVERAGE(E552:H552) -> 1 | J552: Center Alignment
B553: Masters Ntinda | C553: Lmt Account | D553: Salvo Grima Kampala | E553: 1 | F553: 0 | G553: 1 | H553: 1 | I553: =AVERAGE(E553:H553) -> 0.75 | J553: Center Alignment
B554: Mega Standard Supermarket Lweza | C554: Standard Account | D554: Dhl | E554: 0 | F554: 1 | G554: 1 | H554: 1 | I554: =AVERAGE(E554:H554) -> 0.75 | J554: Center Alignment
B555: Miami supermarket | C555: Lmt Account | D555: Mofunds Ltd | E555: 0 | F555: 0 | G555: 0 | H555: 1 | I555: =AVERAGE(E555:H555) -> 0.25 | J555: Center Alignment
B556: Midway Supermarket | C556: Lmt Account | D556: Mofunds Ltd | E556: 0 | F556: 1 | G556: 1 | H556: 1 | I556: =AVERAGE(E556:H556) -> 0.75 | J556: Center Alignment
B557: MILLENIUM 2000 | C557: Lmt Account | D557: Davakam Collections Ltd Kampala | E557: 1 | F557: 1 | G557: 0 | H557: 1 | I557: =AVERAGE(E557:H557) -> 0.75 | J557: Center Alignment
B558: Mirembe shoppers | C558: Lmt Account | D558: Dredro Distributors | E558: 1 | F558: 1 | G558: 1 | H558: 1 | I558: =AVERAGE(E558:H558) -> 1 | J558: Center Alignment
B559: Muzirango And Sons Ltd | C559: Lmt Account | D559: Davakam Collections Ltd Kampala | E559: 1 | F559: 1 | G559: 0 | H559: 1 | I559: =AVERAGE(E559:H559) -> 0.75 | J559: Center Alignment
B560: Nadia Supermarket | C560: Lmt Account | D560: Salvo Grima Masaka | E560: 1 | F560: 1 | G560: 1 | H560: 0 | I560: =AVERAGE(E560:H560) -> 0.75 | J560: Center Alignment
... B614: Wilsen Supermarket | C614: Lmt Account | D614: Davakam Collections Ltd Kampala | E614: 1 | F614: 1 | G614: 1 | H614: 1 | I614: =AVERAGE(E614:H614) -> 1 | J614: Center Alignment
